rpycore/Deployer.py
rpycore/MissionPlanner.py
rpycore/PartsDesigner.py
rpycore/__init__.py
rpycore/libraries/__init__.py
rpycore/libraries/toolbox.py
rpycore/libraries/components/Component.py
rpycore/libraries/components/__init__.py
rpycore/libraries/decorators/__init__.py
rpycore/libraries/decorators/decorators.py
rpycore/libraries/engineers/Engineer.py
rpycore/libraries/engineers/Group.py
rpycore/libraries/engineers/__init__.py
rpycore/libraries/interfaces/Interface.py
rpycore/libraries/interfaces/__init__.py
rpycore/libraries/interfaces/epoxy.py
rpycore/libraries/processes/Process.py
rpycore/libraries/processes/__init__.py
rpycore/libraries/rockets/Rocket.py
rpycore/libraries/rockets/__init__.py
rpycore/libraries/rooms/Room.py
rpycore/libraries/rooms/__init__.py
rpycore/libraries/systems/Constraint.py
rpycore/libraries/systems/__init__.py
rpycore/libraries/tools/Tool.py
rpycore/libraries/tools/__init__.py
rpycore-0.1.1.dist-info/AUTHORS.rst
rpycore-0.1.1.dist-info/LICENSE
rpycore-0.1.1.dist-info/METADATA
rpycore-0.1.1.dist-info/WHEEL
rpycore-0.1.1.dist-info/top_level.txt
rpycore-0.1.1.dist-info/RECORD
