Metadata-Version: 2.1
Name: rpycore
Version: 0.1.1
Summary: A rocket maker.
Home-page: https://github.com/icl-rocketry/RocketPy
Author: Mohammed Raihaan Usman
Author-email: raihaan.usman@gmail.com
License: MIT license
Keywords: rpycore
Platform: UNKNOWN
Classifier: Development Status :: 2 - Pre-Alpha
Classifier: Intended Audience :: Developers
Classifier: License :: OSI Approved :: MIT License
Classifier: Natural Language :: English
Classifier: Programming Language :: Python :: 3
Classifier: Programming Language :: Python :: 3.6
Classifier: Programming Language :: Python :: 3.7
Classifier: Programming Language :: Python :: 3.8
Requires-Python: >=3.6
License-File: LICENSE
License-File: AUTHORS.rst
